{
    "name": "Joerg",
    "main_path": "D:\/Joerg",
    "path_link": "..\/videos\/Joerg",
    "current_directory": "D:\/Joerg\/serien",
    "path_background": "background\/hexagon.jpg",
    "cover_path": "H:\/Covers",
    "show_title": "True",
    "python_path": "python",
    "log": false,
    "elements_per_page": 10,
    "current_page": 5,
    "max_pages": 10,
    "overall_cards": 98,
    "current_file": "D:\/Joerg\/serien\/Alvin und die Chipmunks\/Alvin und die Chipmunks - Folge 01 - Die Fernsehstars - Diebe an Bord.mp4"
}